gnss_tec/__init__.py
gnss_tec/_core.abi3.so
gnss_tec/py.typed
gnss_tec/rinex/__init__.py
gnss_tec/rinex/read_rinex.py
gnss_tec/tec/__init__.py
gnss_tec/tec/bias.py
gnss_tec/tec/constants.py
gnss_tec/tec/mapping_func.py
gnss_tec/tec/tec_calculation.py
pygnss_tec-0.4.0.dist-info/METADATA
pygnss_tec-0.4.0.dist-info/WHEEL
pygnss_tec-0.4.0.dist-info/licenses/LICENSE
pygnss_tec-0.4.0.dist-info/RECORD
