Metadata-Version: 2.4
Name: pygnss-tec
Version: 0.4.0
Classifier: Programming Language :: Python :: 3
Classifier: Programming Language :: Rust
Classifier: License :: OSI Approved :: MIT License
Classifier: Operating System :: OS Independent
Classifier: Topic :: Scientific/Engineering :: Physics
Requires-Dist: numpy>=2.0.0
Requires-Dist: polars>=1.35.0
Requires-Dist: pyarrow>=21.0.0
Requires-Dist: pymap3d>=3.2.0
Requires-Dist: scipy>=1.15.3
License-File: LICENSE
Summary: A Python package for GNSS RINEX file reading and total electron content (TEC) calculation with Rust-accelerated performance.
Keywords: gnss,rinex,tec,ionosphere,python,rust
Author-email: Xinlong Liu <dblxl33236@gmail.com>
License: MIT
Requires-Python: >=3.10
Project-URL: repository, https://github.com/Eureka-0/pygnss-tec.git
